pytest_blue/__init__.py
pytest_blue/plugin.py
pytest_blue-0.0.1.dist-info/entry_points.txt
pytest_blue-0.0.1.dist-info/LICENSE.txt
pytest_blue-0.0.1.dist-info/WHEEL
pytest_blue-0.0.1.dist-info/METADATA
pytest_blue-0.0.1.dist-info/RECORD
