Metadata-Version: 2.1
Name: pytest-blue
Version: 0.0.1
Summary: A pytest plugin that adds a `blue` fixture for printing stuff in blue.
Requires-Python: >3.7
Requires-Dist: rich
Project-URL: Home, https://github.com/okken/pytest-blue
